csv_excel_azure/__init__.py
csv_excel_azure/converter.py
csv_excel_azure-1.1.1.dist-info/LICENSE
csv_excel_azure-1.1.1.dist-info/METADATA
csv_excel_azure-1.1.1.dist-info/WHEEL
csv_excel_azure-1.1.1.dist-info/top_level.txt
csv_excel_azure-1.1.1.dist-info/RECORD
