Metadata-Version: 2.1
Name: csv_excel_azure
Version: 1.1.1
Summary: A package to convert CSV files to Excel on Azure Blob Storage.
Home-page: https://github.com/vipulm124/csv-excel-azure
Author: Vipul Malhotra
Author-email: vipulm124@gmail.com
Classifier: Programming Language :: Python :: 3
Classifier: License :: OSI Approved :: MIT License
Classifier: Operating System :: OS Independent
Requires-Python: >=3.8
License-File: LICENSE
Requires-Dist: azure-storage-blob
Requires-Dist: pandas
Requires-Dist: openpyxl
